{
    "header": {
        "target": "w",
        "formatVersion": 5,
        "hidef": true,
        "compressed": 128
    },
    "readers": [
        {
            "type": "Microsoft.Xna.Framework.Content.DictionaryReader`2[[System.String, mscorlib, Version=4.0.0.0, Culture=neutral, PublicKeyToken=b77a5c561934e089],[System.String, mscorlib, Version=4.0.0.0, Culture=neutral, PublicKeyToken=b77a5c561934e089]]",
            "version": 0
        },
        {
            "type": "Microsoft.Xna.Framework.Content.StringReader",
            "version": 0
        }
    ],
    "content": {
        "Robin": "嘿，你好！^我這裡還有些剩餘的木頭……你或許用得著。請多多保重！^-羅賓 %item object 388 50 %%[#]來自羅賓的禮物",
        "Demetrius": "親愛的 @,^我前幾天做了次實地考察，然後發現了這個標本。^我希望你和我一樣對它感興趣。 ^-德米特里厄斯 %item object 392 1 394 1 132 1 66 1 %%[#]來自德米特里厄斯的禮物",
        "Linus": "你好，朋友。^最近我在山湖那裡的收穫不錯。我想和你分享這份好運。 ^-萊納斯 %item object 136 1 143 1 202 1 227 1 228 1 %%[#]一份來自萊納斯的禮物",
        "Pierre": "尊敬的客戶,^感謝您對皮埃爾商店的惠顧！隨信附上「返利計劃」的退款。祝好！^-皮埃爾^附:股份訊息給您帶來諸多不便，還請諒解 ，@。祝您生活愉快！%item money 250 601 %%[#]來自皮埃爾的禮物",
        "Caroline": "親愛的 @,^這是我在小院裡種的青菜。或許你那裡的蔬菜已經多到連你都不知該怎麼處理了，但沒關係。 ^—卡洛琳%item object 190 1 192 1 24 1 %%[#]來自卡洛琳的禮物",
        "George": "我找到了一些優質石材。^也許你能用它建點什麼。 ^-喬治 %item object 390 35 %%[#]來自喬治的禮物",
        "Evelyn": "你好，親愛的，希望你的農場一切都好。^我在廚房裡做了點東西，給你寄去……但願別在信裡壓碎了。 ^-艾芙琳 %item object 216 1 220 1 223 1 %%[#]來自艾芙琳的禮物",
        "Pam": "嘿。^我在抽屜裡找到了這個。我想你可能用得著。 ^-潘姆 %item object 346 1 349 1 787 1 %%[#]來自潘姆的禮物",
        "Lewis": "@,^很高興你能加入我們的社區！我隨信給你寄了一張來自星露谷農業基金的 500金支票，以資助你繼續努力工作。^或許你能用它買些種子。^此致敬禮，路易斯先生%item money 500 501 %%[#]來自路易斯的禮物",
        "Gus": "@!^今天早上我在酒吧裡給你做了些好吃的。來吃吧！^—你的朋友，格斯%item object 224 1 213 1 211 1 207 1 200 1 195 1 198 1 %%[#]來自格斯的禮物",
        "Clint": "呃，你好……^抱歉，我不怎麼會寫信。我一不小心做多了金屬棒，或許你能用得上。 ^—鐵匠克林特 %item object 334 1 335 1 336 1 %%[#]來自克林特的禮物",
        "Jodi": "親愛的 @,^我給花園訂購了太多肥料了！！我想你應該用得上。請多多保重！^-喬迪 %item object 368 5 369 5 370 5 %%[#]來自喬迪的禮物",
        "Kent": "你好， @。^這東西一直放在工具房裡積灰。我想你也許用得上它。 ^-肯特%item object 286 1 287 1 288 1 787 1 %%[#]來自肯特的禮物",
        "Emily": "嗨！^你還好嗎？希望你能喜歡我給你送去的禮物……那麼，再見！^-艾米麗 %item object 397 1 428 1 440 1 %%[#]來自艾米麗的禮物",
        "Marnie": "親愛的 @,^你是個好鄰居，所以我想送些動物飼料給你，或許能幫得上你的忙。繼續努力吧！^-瑪妮 %item object 178 30 %%[#]來自瑪妮的禮物",
        "Shane": "嘿，^我覺得給你寫信會很有趣。雖然我其實不怎麼會寫。^我隨信附上了一個小禮物。別告訴其他人，這是很久以前我從Joja超市裡搞來的。^好了，待會見。 ^-謝恩 %item object 215 1 206 1 %%[#]來自謝恩的禮物",
        "Wizard": "你好，年輕的術士。^我在包裹裡裝了一隻神器。請謹慎使用。 ^--法師M·拉斯莫迪斯%item object 422 1 82 1 84 1 70 1 %%[#]來自法師的禮物",
        "Sandy": "這是來自卡利科沙漠的問候！^趕緊來看看我吧，我在這裡好無聊：（隨信附上一份來自沙漠的禮物。你可以親自來向我道謝！^-桑迪 %item object 88 1 90 1 218 1 %%[#]來自桑迪的禮物",
        "afterSamShow": "@,^演出取得了巨大成功！我想要再次對你說聲謝謝，是你幫我組建了這支不可思議的樂隊。沒有你，我們成功不了！^-山姆[#]山姆的感謝信",
        "afterArtShow": "親愛的 @,^多謝光臨我的藝術展！簡直太成功了！我幾乎把雕像都賣完了，而大家的肯定是對我巨大的鼓舞！希望很快就能見到你。 ^-莉亞[#]莉亞的感謝信",
        "haleyGarden": "@,^我覺得給你寫封簡訊會很有趣。^昨天我和乳牛玩兒得很盡興……我開始理解你為什麼會選擇田園生活了！希望很快就能見到你。 ^-海莉[#]海莉的簡訊",
        "PennyCleanTrailer": "我要為昨天發生在我家的事情道歉……我媽偶爾會心情不好。^請把不快都忘掉吧。 ^-潘妮[#]潘妮的道歉",
        "Duck": "親愛的 @,^你已經證明了自己養雞的實力，所以我的店裡要開始賣鴨子了！^-瑪妮[#]鴨子開始售賣！",
        "Rabbits": "親愛的 @,^現在我的動物商店裡有兔子！它們能為你提供鬆軟的兔毛……和其他東西！^-瑪妮[#]兔子開始售賣！",
        "Sheep": "親愛的 @,^你已經證明了自己養牛的實力，所以我的店裡要開始賣山羊了！^-瑪妮[#]綿羊開始售賣！",
        "Goats": "親愛的 @,^現在我的動物商店裡有山羊出售！到目前為止你做得很好！^-瑪妮[#]山羊開始售賣！",
        "Pigs": "親愛的 @,^從你剛來時算起，已經取得很多成果。所以，我決定在店裡賣豬。這些豬都受過訓練，能找到美味的松露！^-瑪妮[#]豬開始售賣！",
        "SeaAmulet": "@,^我喜歡你而且想讓你留在鵜鶘鎮，所以我想給你一個建議。如果有一天你想向人求婚的話，你需要給那個人一個「美人魚吊墜」。別擔心，鵜鶘鎮的居民都知道護身符的重要性。這是這片地方的古老傳統。祝您好運！^-路易斯[#]關於美人魚吊墜",
        "Bouquet": "@,^最近你似乎和鎮上的某個人走得很近。如果你想示愛的話，就得送上一束漂亮的鮮花。我這裡賣的花，價錢極其公道！如果你某一天想組建一個家庭，這是第一步！^-皮埃爾[#]關於鮮花",
        "RobinCooking": "親愛的 @,^這是我奶奶傳授給我的古老配方。祝您生活愉快！^-羅賓%item cookingRecipe %%[#]羅賓的祖傳配方",
        "DemetriusCooking": "德米特里厄斯我想感謝你對我工作的支持。這是一份我喜歡的烹飪食譜。 ^-德米特里厄斯%item cookingRecipe %%[#]德米特里厄斯的食譜",
        "LinusCooking": "@,^你最近過的怎麼樣？我隨信附上了我最愛的魚料理做法。 ^-萊納斯%item cookingRecipe %%[#]萊納斯的食譜",
        "PierreCooking": "最高機密：^這是我著名的藍莓撻配方。^別告訴任何人哦！我之所以把它給你，是因為你是我的好朋友。 ^-皮埃爾%item cookingRecipe %%[#]皮埃爾的著名藍莓撻",
        "CarolineCooking": "親愛的 @,^沒有什麼能比用自己種的菜做飯更讓人滿足的了！我隨信附上了一份食譜。照顧好自己。 ^—卡洛琳%item cookingRecipe %%[#]卡洛琳的食譜",
        "GeorgeCooking": "這份配方我留著也沒用，索性給你試試吧。小心別把它燒了。 ^-喬治%item cookingRecipe %%[#]喬治的食譜",
        "EvelynCooking": "親愛的 @,^我一般不把我的配方告訴別人……但是你對我和喬治都太好了，所以我把這份配方送給你。 ^-艾芙琳%item cookingRecipe %%[#]艾芙琳的配方",
        "PamCooking": "孩子你好，^這是我老爸常做的一道小菜的配方。要小火慢燉才行。 ^-潘姆%item cookingRecipe %%[#]潘姆的配方",
        "LewisCooking": "@,^要注意健康飲食，才能有足夠的體力工作！隨信附上一份我最愛的配方。記著要用熟的番茄。^-路易斯%item cookingRecipe %%[#]路易斯的配方",
        "GusCooking": "親愛的 @,^這是我酒吧的食譜。我只和好朋友分享這個！^-格斯%item cookingRecipe %%[#]格斯的配方",
        "ClintCooking": "嗯，我倒是知道兩三種配方。^告訴你一種的話……或許能幫你多開採些礦石也說不定。^保重。 ^-克林特%item cookingRecipe %%[#]克林特的配方",
        "JodiCooking": "@,^這份食譜曾幫我在烹飪比賽裡贏得第一名！希望你喜歡。就算是朋友的謝禮吧！^-喬迪%item cookingRecipe %%[#]喬迪的配方",
        "KentCooking": "我是在國外發現的這份配方。盡情品嘗吧。^我想要對你的好客說聲謝謝。 ^^-肯特%item cookingRecipe %%[#]肯特的配方",
        "EmilyCooking": "@!^把這封信翻過來，上面寫有一種超級健康的飯菜做法！^那會讓你感覺精力充沛。那一會見囉！ ^-艾米麗%item cookingRecipe %%[#]艾米麗的健康食譜",
        "MarnieCooking": "親愛的鄰居，^在照料動物之餘，我喜歡在廚房裡做些新嘗試。既然我們成為了朋友，我想和你分享一些我的配方。^希望你能喜歡！^-瑪妮%item cookingRecipe %%[#]瑪妮的配方",
        "ShaneCooking": "@,^我在雜誌上看到了這個配方，看起來挺有意思的。如果你照著做了，不妨讓我嚐嚐吧。 ^-謝恩%item cookingRecipe %%[#]謝恩的配方",
        "SandyCooking": "親愛的 @,^我在沙漠裡好無聊，所以給你寫了這封信。隨信附上一種靚湯的配方。趕緊來看看我吧！^-桑迪%item cookingRecipe %%[#]桑迪的配方",
        "WillyCooking": "親愛的 @,^我想分享爸爸曾經發明的一道菜餚。其中的精髓就在於魚要百分百新鮮！ ^-威利%item cookingRecipe %%[#]威利的配方",
        "mom1": "親愛的 @,^寶貝，你最近過的怎麼樣？你走了我真是朝思夜想。我希望農場上的生活是你期望的那樣。^愛你的媽媽。^附：我把你最喜歡的餅乾寄給你了。 %item object 223 1 %%[#]媽媽的信",
        "mom2": "\n        親愛的 @,^很久沒收到你的來信了。家裡還是和回來的時候一樣。我非常想你。^愛你的媽媽。 ^我收拾到一個裝著一些錢的信封，那是你爺爺留下來給你的。 %item money 500 501 %%[#]媽媽的信 #2",
        "mom3": "親愛的 @,^我在報紙上看到關於你的報導了！鄉村生活看起來很合你胃口呢！我真的為你感到自豪。好好照顧你自己，我的小甜心。愛你的媽媽。[#]媽媽的信 #3",
        "mom4": "親愛的 @,^最近過的怎麼樣啊？你一定在農場那邊賺了很多錢吧！就算變成百萬富翁也別忘記你的老媽哦！^愛你的媽媽。 ^附：好好享用蛋糕吧！%item object 221 1 %%[#]媽媽的信 #4",
        "dad1": "親愛的 @,^你在那裡安頓下來了嗎？真是不敢相信你已經長大成人了啊……時間真是快。現在你在外地，我手頭存了很多錢，所以我還給你寄了一個小禮物。^愛你的爸爸。%item money 500 501 %%[#]爸爸的信",
        "dad2": "親愛的 @,^鄉下生活還適應嗎？雖然你不在我身邊了，但是我一直為你感到自豪。^愛你的爸爸 ^我收拾到一個裝著一些錢的信封，那是你爺爺留下來給你的。 %item money 500 501 %%[#]爸爸的信 #2",
        "dad3": "親愛的 @,^我在報紙上有看到你的報導！你竟然變得那麼優秀了！繼續加油，說不定你爹可以在熱帶小島上，住著小房子，過著奢侈的退休生活呢！^愛你的爸爸[#]爸爸的信 #3",
        "dad4": "親愛的 @,^聽說你在農場忙的都沒辦法來探望我們，沒事我們理解的，你一直都那麼努力……世上無難事只怕有心人，加油！^愛你的爸爸 ^附：我給你寄了些很棒的石頭 %item object 390 30 %%[#]爸爸的信 #4",
        "newsstory": "您好， @。^很高興地通知您我們會在星露谷論壇下週的「活力」專欄介紹貴農場！祝賀你！您的顯著進步令我們印象深刻。 ^—星露谷論壇[#]新聞故事",
        "pierreBackpack": "廣告：^雖然我的背包已經裝不下了，但我還是在繼續尋找更酷的東西！^^是不是很像你？哈哈，有皮埃爾在就高枕無憂了。^^今天光臨皮埃爾商店，看看價廉物美的 24號背包！^祝好！[#]皮埃爾商店的背包",
        "pierreHours": "廣告：^^皮埃爾商店每週7天都不休息！[#]皮埃爾商店延長時間",
        "robinKitchenLetter": "親愛的農夫 @,^^我們第一次見面的時候我嘲笑了你爺爺的老木屋，我現在想向你道歉。它其實是一間很不錯的屋子！^^然而，也許有一天你會需要擴展出更多的空間。那時我就能幫上忙了。如果你能帶給我一些原材料，並且支付一定的費用的話，我就能幫你擴建你的房子。^^我首先計劃幫你擴建出一間廚房。有了廚房，你就可以在那裡弄你新學習的菜單了！^^總之，我希望你把星露谷當成自己的家鄉！^^星露谷的木匠^羅賓 [#]羅賓的服務",
        "taxPassed": "親愛的 @,^航運稅已經開始徵收了。現在，我們會從你的營運利潤中徵收3%的稅款。公共服務的開支也已經被縮減了。祝好！^-鎮長[#]稅收案通過",
        "taxRejected": "親愛的 @,^徵收航運稅的方案被拒絕了。我們不會對你航運利潤進行徵稅，公共服務的撥款也會維持不變。歡迎光臨！ ^-鎮長[#]稅收案拒絕",
        "quest10": "@,^我聽說你最近一直對鎮上的人們施以援手！大家都很感激你！因此我想把本月的\"最佳鄰居\" 獎授予你（同時你會獲得一點現金鼓勵）。繼續努力吧！^-鎮長%item money 500 501 %%[#]最佳鄰居",
        "quest35": "親愛的@：^你搬來鎮上之後，一直都很樂於助人……大家都一直向我誇讚你！請收下這份謝禮。^——鎮長%item money 2500 2501 %%[#]路易斯的謝禮",
        "quest100": "@,^我很高興宣布你當選了\"年度最佳鄰居\"！獎金有整整 10,000金哦！衷心地祝賀你！鎮上的鄉親們都折服於你的高尚行為！ ^-鎮長%item money 10000 10001 %%[#]年度最佳鄰居",
        "hero_update": "@,^現在是時候揭曉本季度星露谷英雄的排名了！我把排名藏在了一個單獨的信封裡。祝你們這個季度好運！^-鎮長[#]星露谷英雄排名",
        "hero_update1": "%更新",
        "CF_Fish": "親愛的 @,^你的釣魚技術比我家老頭子還厲害啊！我很震撼。^這個星之果實從老威利傳到小威利，再傳到……哇。反正有快一千年的歷史了。^我，膝下無子……乾脆把他傳給你吧。^^-威利 ^%item object 434 1 %%[#]威利的傳家寶",
        "adoptionLetter": "親愛的 @和您的愛人。^衷心地祝賀你！你的收養申請已通過審查！^我們現在正努力為您挑選與您相配的完美嬰兒。^小寶寶會在兩週內和你們見面。^^-芬吉爾領養機構[#]領養通知",
        "stardewHeroMine": "秘密訊息:如果你能再一次下到礦井底部的話，你會發現有一個秘密在等著你發掘。但是小心點，現在礦井越來越危險了。[#]秘密訊息",
        "fertilizers": "親愛的鄰居，^希望你已經安頓好自己的新家了。我寫信是想告訴你皮埃爾的雜貨店進了一批肥料！要不要去雜貨店那裡看看有什麼要買的呢？ ^-皮埃爾 [#]皮埃爾的肥料",
        "fertilizers2": "親愛的 @,^現在店裡進了一批高品質的化肥和新的穀物種子！歡迎光臨！ ^-皮埃爾[#]皮埃爾的高品質肥料",
        "abbySpiritBoard": "嗨 @。^這幾天晚上你可以抽空來我家坐坐……大概晚上八點吧。^我有樣東西要給你看。 ^ -阿比蓋爾[#]阿比蓋爾的筆記",
        "pennySpa": "晚上到澡堂來見我 ^-潘妮[#]潘妮的筆記",
        "incubator": "親愛的 @,^^感謝你選擇購買雞舍升級服務！我不僅讓你的雞舍容量翻了一倍，我還幫你安裝了孵化器。^你只要把雞蛋放入孵化器即可。只要你的雞舍還有位置，過不了幾天雞蛋就會孵化啦。^^很感謝您的光臨。^-羅賓[#]關於孵化器",
        "hatter": "嗨。^^窩賣帽子。聽懂了嗎，波克？^^波克，到破房茲這裡來。帶點金閉。^^——帽子老鼠[#]嗨喲，波克",
        "Beat_PK": "恭喜你！！！^^你通關了「草原之王的冒險之旅」並被我們選為特別獎勵獲得者！^你贏得了專屬於你自己的草原之王的冒險之旅遊戲系統！^現在你可以在家享受「草原之王的冒險之旅」帶來的樂趣！^^這是你的獎賞！^-草原之王的冒險之旅開發團隊 %item bigobject 141 %%[#]草原之王的冒險之旅的祝賀",
        "JunimoKart": "恭喜你！！！^^你通關了，你是芬吉爾共和國第一個通過的人！^你的獎勵：一台家庭版的祝尼魔賽車！^^好好享受遊戲！^-祝尼魔賽車開發團隊 %item bigobject 159 %%[#]祝尼魔賽車通關！",
        "elliottReading": "@,^我有個天大的好消息……我寫完我的小說了！我下午會在圖書館前舉行一個公開的閱讀會。你一定要來！^-艾利歐特[#]艾利歐特的閱讀會",
        "elliottBoat": "找一天晴朗的清晨到碼頭來找我。我有些話想和你說。 ^-艾利歐特[#]艾利歐特的筆記",
        "harveyBalloon": "@,^我想給你一個驚喜。在鐵軌旁等我。 ^-哈維[#]哈維的驚喜",
        "samMessage": "@,^天黑後在我家門前等我 ^-山姆[#]山姆的筆記",
        "joshMessage": "@,^天黑後到酒館見我。 ^-亞歷克斯[#]亞歷克斯的邀請",
        "lewisStatue": "@，^^今後，如果你能不把我的私人物品放在城裡讓所有人都看到，我會非常感激！^^我很不高興！^^拿上這筆錢，不要向任何人提起我的「項目」。%item money 750 751 %%[#]路易斯的抱怨信",
        "marnieAutoGrabber": "@：^我的存貨中新添了一件東西……叫做「自動採集器」。^^這件東西可以給乳牛和山羊擠奶、給綿羊剪羊毛、拾取雞蛋和鴨毛……一切全自動！^^堪稱是「奢侈品」，所以我開價 25,000 金。^^——瑪妮[#]自動採集器通知",
        "EmilyClothingTherapy": "@，^我有了一個瘋狂的新想法，我想你了解……所謂的「服裝療法」。^^請在今天去鎮長的家裡，了解它是關於什麼的。^^愛你，艾米麗[#]艾米麗的想法",
        "EmilyCamping": "@，^我們去野營吧！^^晚上10點後我們在秘密森林見。^^愛你，艾米麗[#]艾米麗的邀請",
        "EmilyDoneCamping": "昨晚，謝謝你赴約……我度過了一段美好的時光。^我真的很感激熊的出現！^^再見^^愛你，艾米麗[#]艾米麗的筆記",
        "foundLostTools": "親愛的@：^昨晚有人找到你的工具，放進失物招領箱了。^^到鎮長辦公室來拿吧。^^——鎮長路易斯[#]遺失的工具",
        "fishing2": "我進了一些新貨品！^豪華釣竿，你可以在上面放置餌料！^你可以使用餌料讓魚更快地上鉤！歡迎前來購買！^-威利[#]威利的新貨品",
        "fishing6": "快來看一看瞧一瞧，新品魚竿上市囉。^貨真價實，你還可以裝備不同的釣具！^歡迎前來選購！^-威利[#]威利的新貨品 #2",
        "wizardJunimoNote": "我的訊息源告訴我，你一直在舊社區活動中心附近溜達。^何不來拜訪我一趟？^我住在森林湖西邊的石塔裡。關於你那……「老鼠肆虐」的問題，我也許有一些線索。^--法師M·拉斯莫迪斯 %item quest 1 true %%[#]法師的召集",
        "winter_18": "親愛的 @,^我想和你說一下最近的節日和盛事：冬日星盛宴。在這個節日裡我們歡聚在一起，回憶過去的一年我們的勞動成果。^我們有一項好玩的傳統 \"秘密禮物交換\"，每個人都會隨機分配到一位朋友。在宴會的那天，大家都會拿出精心準備的禮物讓你的朋友大吃一驚！^今年，你的「神秘朋友」是:^%secretsanta ^別告訴任何人哦！宴會在25號的10點到2點，在鎮上的廣場舉行。不見不散！^-鎮長路易斯[#]秘密的送禮人",
        "ccBulletinThankYou": "親愛的 @,^最近鎮上的鄉親都在褒揚你的大方呢！^最近，人們都收到了不同的包裹，包裹裡都是他們很早之前在社區活動中心公告欄裡求購的東西。這些包裹都是從你的農場寄出的！^真的很感激你高尚的行為，鄉親們都很開心！^-鎮長路易斯 [#]公告欄的感謝",
        "guildQuest": "我發現你一直在探索那個舊礦井。我只能說，你生來就是個探險者。^只要擊殺10隻史萊姆， 你就能在我的探險家公會裡擁有一席之地。^小心點。——馬龍 %item quest 15 true %%[#]史萊姆擊殺任務",
        "skullCave": "我看到你之前曾進入到頭骨山洞裡。做得好。^年輕人，我有一個更大的挑戰要交給你。等你達到至少25層的時候才算是完成任務。如果你能完成任務的話，我會給你一座山的 $ 。^你的朋友，齊先生 %item quest 20 %%[#]齊先生的挑戰",
        "robinWell": "我是羅賓！^我了解到你的農場周圍有很多散落的碎石。^如果碎石有富餘的話，你或許可以考慮讓我給你建口井。^井可以建在農場裡的任何地方，這樣你給噴壺打水就更方便了。^^等你準備好了，帶上75 個石頭 和 1000金來我店裡就行。^-羅賓[#]建一口井",
        "landslideDone": "尊敬的Joja超市的顧客：^我們的團隊成員已經清理了山崩現場，這次山崩是受到我們公司鑽井活動的影響。我們必須聲明我們的鑽井活動是完全合法的（依據Joja公司第L61091修正案）而保護當地環境一直都是我們的優先考量！^^我們對這次的意外帶來的不便深感歉意。^我們由衷地對顧客的支持和贊助表示感謝！^^-莫里斯^Joja顧客滿意部門代表[#]Joja清理滑坡",
        "QiChallengeComplete": "你成功了！^我對你真是刮目相看。^這是你的獎勵！^——齊先生 %item money 10000 %%[#]齊先生的挑戰完成",
        "spring_2_1": "你好啊，^我剛剛釣完魚回來。你偶爾也該來沙灘走走。^我有些東西要給你。^-威利 %item quest 13 true %%[#]威利的邀請",
        "spring_12": "親愛的 @,^明天我們會在廣場歡慶復活節。^^如果你想和我們一起慶祝的話， 請在上午9點到下午2點之間到位。^一年一度的彩蛋大尋寶不容錯過！^-鎮長路易斯[#]歡慶復活節通知",
        "spring_15_1": "你好呀，親愛的……^^我了解到你剛剛開始種菜，所以我想給你一個小小的提示。^^大多數作物只能生長一季。等夏天到了的時候，你在春天種的所有作物就都會枯萎。所以你要提前計劃好！^^-艾芙琳奶奶[#]艾芙琳的提示",
        "spring_23": "親愛的 @,^明天就是花舞節了！^^你可以邀請一位舞伴，和我們一起起舞。^我們會在小鎮西邊森林後的空地舉行舞會。如果你感興趣， 請在上午9點到下午2點出席。^-鎮長路易斯[#]花舞節通知",
        "summer_10": "親愛的 @,^明天我們會聚集在沙灘上，慶祝一年一度的鵜鶘鎮宴會。^^這個盛宴的高潮就在於共享百樂餐。記得把好吃的貢獻出來哦！^州長也會親臨現場，請注意自己的言行。^請在上午9點到下午2點之間到沙灘出席宴會^-鎮長路易斯 [#]宴會通知",
        "summer_28": "親愛的 @,^今晚大約10點鐘，會舉行一項極其罕見但絢麗的盛事。^^月光水母在他們冬天往南遷徙的旅途上會經過鵜鶘鎮！^^我們都會聚在沙灘上一起觀賞。可不要錯過哦！^今晚見，^-德米特里厄斯[#]月光水母之舞",
        "fall_9": "親愛的 @,^我們將在一週後的今天舉辦星露谷展覽會！^這項年度盛事會吸引全國各地的人們來到我們這個平和的小鎮！^如果你想參加的話，你可以進行農莊展覽。你只需要帶上最能展示你才華的九份展覽品。將對你的展品品質和品種進行評價！^展覽會會在上午9點開始，別錯過哦！^-鎮長路易斯[#]星露谷展會通知",
        "fall_15": "親愛的 @,^我想你一定知道明天就是星露谷展覽會了吧。^記得帶上九件物品來參加農莊展覽。^注意，博覽會會在明天上午9點在鎮上廣場舉行。期待你的參與！^-鎮長路易斯[#]星露谷展會提醒",
        "fall_26": "親愛的 @,^不知道你有沒有注意到寒氣，冬天可能要來了……^不然就是黑暗的遊魂，呼嘯著和我們一起慶祝今天的節日……萬靈節！^晚上10點來鎮裡 和我們一起慶祝吧。^-鎮長路易斯 [#]萬靈節通知",
        "winter_7": "親愛的 @：^明天我們會在瑪妮家前集合，慶祝冰雪節。^^這是我們歡慶冬天的日子……我們會堆雪人、做冰雕，還會有釣魚比賽呢！^如果你感興趣，早上9點到下午2點左右來和我們一起慶祝吧。^——鎮長路易斯[#]冰雪節通知",
        "winter_14": "從明天開始，一個旅行商隊將在鵜鶘鎮停留，以參加每年一次的夜市。^^夜市從下午5時開始，並在接下來的三天內在港口內舉行。^^下午5時後請到海灘參加慶祝活動。有免費咖啡！[#]夜市通知",
        "spring_11_1": "尋物啟事：^我把我的愛斧丟了！有誰撿到的話請即刻歸還。沒有它我非常不方便！任何找到它的人都能得到 250金的獎勵。^-羅賓%item quest 100 %%[#]羅賓弄丟了斧頭",
        "spring_19_1": "農夫  @,^你可以幫幫我嗎，我需要花椰菜做一道菜，你可以給我點嗎？^-喬迪%item quest 101 %%[#]喬迪需要花椰菜",
        "summer_3_1": "@-^這有點尷尬了。我把我的幸運紫色短褲丟了。我只告訴你，因為我信任你。^如果你能幫我找到，請妥善歸還。我會給你豐富報酬的哦。^麻煩你了。^-鎮長路易斯%item quest 102 %%[#]路易斯需要幫助",
        "summer_14_1": "孩子你好，^我的喉嚨要乾透了。我真的很渴望喝一點淡啤酒。你有淡啤酒嗎？普通的老啤酒不會有用的。一定要是淡啤酒啊。^-潘姆%item quest 103 %%[#]潘姆的請求",
        "summer_20_1": "@-^我在收集數據以驗證土地酸鹼度和作物果糖濃度的關係。簡單地說，我需要一顆來自你的農場的甜瓜。如果你能送一個給我的話，我會非常感激的。^-德米特里厄斯%item quest 104 %%[#]德米特里厄斯請求樣本",
        "summer_25_1": "致農夫 @：^我的膝蓋又痛了，你還有什麼方子嗎？^把辣椒抹在那該死的膝蓋上。^問題是，我的儲備已經空了。如果你有多餘的辣椒可以給我的話，我會非常感激。^-喬治 %item quest 105 %%[#]喬治需要辣椒",
        "fall_3_1": "親愛的 @,^我想給我的乳牛們搞些好吃的。這些乳牛棒極了，就是有點餓，你能幫我搞到一把莧菜嗎。它們很愛莧菜。^麻煩你了，親愛的^-瑪妮 %item quest 106 %%[#]瑪妮的請求",
        "fall_8_1": "你好，^又到了黑莓成熟的季節。外面的草叢裡都是黑莓，我想摘點回去，但是我找不到我的籃子了。你可以幫我嗎？^-萊納斯%item quest 107 %%[#]萊納斯弄丟了籃子",
        "fall_19_1": "@-^我想買個南瓜。我和女兒想在萬靈節刻一個南瓜燈。 ^—卡洛琳%item quest 108 %%[#]卡洛琳的請求",
        "winter_2_1": "嘿，幫我個忙吧：^    幫我抓隻魷魚。^你可以晚上去大海裡面找找。不過他們只在冬天出現。^-威利%item quest 109 %%[#]威利的挑戰",
        "winter_6_1": "我有個特殊的請求。你可以不跟別人說嘛？^幫我把紫水晶交給艾米麗。這是她最喜愛的寶石。記得跟她說是我送她的。^-克林特 %item quest 110 %%[#]克林特特殊請求",
        "winter_12_1": "@-^我現在正在研究影子占卜這項失傳的法術。我需要「虛空精華」進行我的研究。幫我找到它我會給你報酬的。^--法師M·拉斯莫迪斯 %item quest 111 %%[#]法師的請求",
        "winter_17_1": "@,^不好意思又來煩你了，但是我這次需要你來幫忙。^我想試試我的新鐵錘敲不同金屬會怎樣。^你可以幫我煉一條鐵錠給我嗎?^麻煩你了。^-克林特 %item quest 112 %%[#]克林特的請求",
        "winter_21_1": "@-^你還好嗎？這個冬天不會太難熬吧？^總之，我想問問你有沒有硬木。有的話給我十塊。^沒有的話就算了。保重！^-羅賓%item quest 113 %%[#]羅賓的請求",
        "winter_26_1": "親愛的 @-^我想要燉一鍋魚！我知道這個季節不好找……突然這樣拜託你有點強人所難。但是你能幫我抓到一條回來嗎？^-格斯%item quest 114 %%[#]格斯需要一種魚",
        "spring_1_2": "通知：^^羅賓商店和克林特商店的原材料價格已經上漲。[#]原材料漲價通知",
        "spring_6_2": "@——^我好想要一個新鮮的杏子啊。但是商店裡沒有賣的，如果你能幫我弄到的話。我會給你很多報酬的！^——艾米麗%item quest 115 %%[#]艾米麗的請求",
        "spring_15_2": "親愛的 @,^我想給我的丈夫一份特別的禮物。他特別喜歡大蔥，你可以給我點嗎？^-艾芙琳奶奶%item quest 116 %%[#]艾芙琳的驚喜",
        "spring_21_2": "通知^皮埃爾有話要說……我想吃生魚片想瘋了。誰給我帶一點生魚片我會給他報酬的。^-皮埃爾%item quest 117 %%[#]皮埃爾的渴求",
        "summer_6_2": "招聘漁夫^需要一條完美的河豚標本。我在進行河豚毒素的實驗。^獎勵：1000金^-德米特里厄斯%item quest 118 %%[#]德米特里厄斯的毒素實驗",
        "summer_15_2": "親愛的農夫 @,^我想在結婚紀念日的時候送給妻子一顆楊桃。你在農場裡種楊桃了嗎？如果你能給我帶一個的話，我會很感激你的。^-肯特%item quest 119 %%[#]肯特需要一個禮物",
        "summer_21_2": "@,^我需要松露油。別問原因。^-鎮長路易斯%item quest 120 %%[#]路易斯的請求",
        "fall_6_2": "徵集：我需要一隻新鮮的龍蝦來製作美妙的濃湯。^徵集人：星果酒吧的老闆格斯^獎勵：800金 %item quest 121 %%[#]格斯需要龍蝦",
        "fall_19_2": "通知^有誰有電池嗎？我電視遙控器沒電了，我實在懶得從椅子上下來去換台了。^-潘姆%item quest 122 %%[#]潘姆需要幫助",
        "winter_5_2": "@,^我在製作一支蘊藏有驚人力量的法杖。^但是,我現在需要一個銥錠！^我願意出5倍的市價買它。快點幫我搞到。^--法師M·拉斯莫迪斯 %item quest 123 %%[#]法師需要稀有物品",
        "winter_13_2": "我又有一項挑戰要來考考你：抓一條蛇齒單線魚！^這東西不好搞，但我知道你能做到的^-威利%item quest 124 %%[#]威利的挑戰#2",
        "winter_19_2": "親愛的 @,^我束手無策了。我想在我的酒吧調一杯椰子酒，但是我不知道怎麼才能搞到椰子！^你能幫幫我嗎？^-格斯%item quest 125 %%[#]格斯需要椰子",
        "winter_24": "親愛的 @,^明天就是冬日星盛宴了！^你有沒有為你的「神秘朋友」%secretsanta精心準備一份禮物呢？^宴會在鎮裡的廣場舉行，九點開始。不見不散！^-鎮長路易斯[#]冬日星盛宴提醒",
        "passedOut1_Billed_Male": "親愛的 @先生！^昨晚，Joja團隊的一位員工發現您昏倒了。我們派出了一支醫療小隊來把您安全地送回了家裡。^很高興您沒有出事！^^（這個服務會向您收取 {0}金的費用）^^-莫里斯^Joja顧客滿意部門代表[#]Joja的帳單",
        "passedOut1_Billed_Female": "親愛的 @小姐！^昨晚，Joja團隊的一位員工發現您昏倒了。我們派出了一支醫療小隊來把您安全地送回了家裡。^很高興您沒有出事！^^（這個服務會向您收取 {0}金的費用）^^-莫里斯^Joja顧客滿意部門代表[#]Joja的帳單",
        "passedOut1_NotBilled_Male": "親愛的 @先生！^昨晚，Joja團隊的一位員工發現您昏倒了。我們派出了一支醫療小隊來把您安全地送回了家裡。^很高興您沒有出事！^^由於您沒有錢，根據法律我們有義務向您提供免費服務。^^-莫里斯^Joja顧客滿意部門代表[#]法律要求的通知",
        "passedOut1_NotBilled_Female": "親愛的@小姐！^昨晚，Joja團隊的一位員工發現您昏倒了。我們派出了一支醫療小隊來把您安全地送回了家裡。^很高興您沒有出事！^^由於您沒有錢，根據法律我們有義務向您提供免費服務。^^-莫里斯^Joja顧客滿意部門代表[#]法律要求的通知",
        "passedOut2": "@, ^你真幸運，我昨晚找到你了！你都沒有意識了，而且有人在翻你的口袋。我不知道他們拿走了你多少錢……我接近你的時候他們迅速跑走了。要多加小心啊！^^-萊納斯[#]萊納斯的筆記",
        "passedOut3_Billed": "@,^昨晚有人將你送到診所了。你因中暑而暈倒！^你要照顧好自己，並在合適的時間及時睡覺。^你的醫療費是 {0}金。^^-哈維醫生[#]來自哈維醫生的辦公室",
        "passedOut3_NotBilled": "@,^昨晚有人將你送到診所了。你因中暑而暈倒！^你要照顧好自己，並在合適的時間及時睡覺。^由於你沒有錢，我想你提供免費的醫療服務。^^-哈維醫生[#]哈維免費的醫療服務",
        "passedOut4": "@：^^我在凌晨三點清掃的時候發現你趴在泥地裡。^^下次你應該儘可能早一點回家！^^     ——馬龍[#]馬龍的便條",
        "elliottLetter1": "親愛的@：^^我剛到格蘭普立頓開始巡迴。我都忘了這座城市有多繁忙！街道上擠滿了人……他們要嘛看起來很匆忙，要嘛迷茫，對周圍的環境毫無感覺。我已經開始懷念鵜鶘鎮了！^^我今晚在當地的一家書店開始閱讀會。我必須承認，一想到要公開演講，我就有點緊張……我的胃感覺好像被擰成了一個柔軟的椒鹽脆餅，蘸上了辛辣的乳酪。祝我好運！^^——愛你的，艾利歐特^^P.S. 我希望你度過了一個平靜的夜晚，一個人在大房子裡不要害怕！ %item conversationTopic ElliottGone2 0 %%[#]我丈夫的信",
        "elliottLetter2": "親愛的@：^^我的第一次閱讀會還不錯，儘管觀眾比我期望的要少一些。不過，我還是賣了挺多的書，足夠支付我的旅館房間費用！（雖然蟲子很多）^^過幾個小時，我就要動身前往祖祖城。如果把昨天的閱讀會比作熱身運動的話, 接下來這一場就像真槍實彈了……^^我很想你。記住要好好吃飯！哦，還有，別忘了我剩了些蟹黃糕在冰箱裡……^——愛你的，艾利歐特 %item conversationTopic ElliottGone3 0 %%[#]我丈夫的信 2",
        "elliottLetter3": "我親愛的@：^^昨晚在祖祖城的經歷十分棒！看起來是一個巨大的文學集會……我的讀書會上有幾十個人！^^我甚至簽了幾張簽名……被看做知名人士讓我感覺很彆扭。這只是一個錯覺……事實上我一點也不特別。只是你摯愛的艾利歐特，一如既往。^^現在我獨自一人，在我的酒店房間，「攝入」了一頓Joja超值餐……^^這應該叫「食物」還是「可食用的物質」？^不用多想^肯定是後者^^我期待能夠早點回家，希望你喜歡蟹黃糕。^^——愛你的，艾利歐特 %item conversationTopic ElliottGone4 0 %%[#]我丈夫的信 3",
        "elliottLetter4": "在夢中，當我仰望遠眺時^我凝視著陽光照耀的大海^凝視著我所走過的遙遠的海岸^但時間模糊了我的記憶^^永恆的地方只有一個^我總有一天會經過那裡^是在可愛的山谷裡，有我的愛人在等待：^我們在池塘邊的小家^^——艾利歐特 %item conversationTopic ElliottGone5 0 %%[#]我丈夫的信 4",
        "elliottLetter5": "親愛的@：^^我不會再寫閱讀會的細節讓你感到無聊了。它們基本都差不多。^^我相信你的經歷一定更令人興奮！我迫不及待地想回來看看都發生了什麼事。^^在城鎮之間的長途旅行中，我閉上眼睛，想像著農場，讓自己更開心……我看見酒桶裡擺著甜酒，爐子裡燃燒著珍貴的礦石，還有我們的小廚房裡有肉桂和肉豆蔻的味道。有很多東西可以享受！^^親愛的，別在礦井裡待得太晚。裡面很危險！如果你非得去……要帶上足夠的食物。^^——愛你的，艾利歐特 %item conversationTopic ElliottGone6 0 %%[#]我丈夫的信 5",
        "elliottLetter6": "親愛的@：^^這是我回家前的最後一封信了。我的旅程十分愉快……雖然沒什麼十分激動人心的事情。能見到喜歡我的書的人讓我很高興，但我還是渴望回家。^^我想念我們舒適的小房子，令人滿足的農事，一頓家常菜，當然最想念的，是和你一起舒適地躺在法蘭絨的床單上。^^盼早日見到你！^——愛你的，艾利歐特 %item conversationTopic ElliottGone7 0 %%[#]我丈夫的信 6",
        "MarlonRecovery": "@：^你遺失的物品找到了。^^下次細心點！^   ——馬龍%item itemRecovery %%[#]馬龍找到了你的東西",
        "RarecrowSociety": "親愛的@：^^您的貢獻令人讚嘆……^^只有少數人能夠收集全套珍奇烏鴉系列！！^^請收下這張圖紙以紀念你的成就。^   ——Z.C. 珍奇烏鴉協會%item craftingRecipe Deluxe_Scarecrow %%[#]珍奇烏鴉協會來信",
        "CarolineTea": "親愛的@：^^感謝你昨天來我的日光房做客。我經常獨自喝茶，但和你一起享用真的很愉快！^^我隨信附上了自己種植茶葉的前期準備和具體步驟。不要有壓力，不過如果你最後種植成功了，請一定要給我帶一杯你的茶！^^——卡洛琳%item craftingRecipe Tea_Sapling %%[#]卡洛琳的種茶筆記",
        "WoodChipper": "你好，@：^^我想告訴你我們進了一個新東西……它叫做「碎木機」。^^你可以用它把硬木削成幾塊普通木頭！^^我知道冬天很難找到木材，所以如果木材不太夠了，可以考慮買一個。^       ——羅賓[#]碎木機提示",
        "willyBackRoomInvitation": "@：^^我把商店後面的裡屋打開了。^如果有空的話請過來一下。^我有點東西想給你看看。^^——威利[#]威利邀請去裡屋",
        "KrobusCrafting": "@，我不知道人類的信是怎麼寫的，所以我請法師幫我寫了這封信。^^希望你一切都好。^^我想給你看看這個……是我的同族人製作一樣東西的筆記……^^——科羅布斯%item craftingRecipe Dark_Sign %%[#]來自科羅布斯的信",
        "georgeGifts": "親愛的@：^^謝謝你送來的韭蔥，看起來新鮮而且美味。喬治會喜歡的。^^今天我要用 12 份包裝好的小禮物給他一個驚喜！（多虧有你幫忙！）你可以過來看看！^^——艾芙琳^^P.S. 請收下這份禮物，你會喜歡的！%item bigobject 246 %%[#]艾芙琳的感謝信",
        "robinResource": "@：^^你好！^^恭喜你完成了我的小挑戰。你太棒了！^^我附上了一種新型箱子的設計圖，就當作額外的獎勵。希望你喜歡！^^——羅賓^^^^P.S. 既然你已經有這麼多資源了，要不要來試試做些建築工程？%item craftingRecipe Stone_Chest %%[#]羅賓的資源活動",
        "ClintReward": "呃，你好……^謝謝你幫我清掉了那些怪物。^^我一點也不害怕的！……但是維護礦井的安全是有必要的，對大家都好……是不是？^^給你這個設計圖。（有了這個也別忘了光顧我的鋪子啊……）^^——鐵匠克林特%item craftingRecipe Geode_Crusher %%[#]克林特的感謝",
        "ClintReward2": "呃，你好……^謝謝你幫我清掉了更多怪物。^^也許下次我就能自己收拾它們了……如果我有空！^^給你這個，是我在裡屋找到的……^^——鐵匠克林特%item object 286 10 287 5 231 3 %%[#]克林特的再次感謝",
        "willyBugWadCutscene": "^^——威利%item craftingRecipe Quality_Bobber %%[#]威利的感謝",
        "MSB_Pierre": "親愛的@：^^似乎人們對我的「皮埃爾優選」不感興趣，有點失望……^^不說了。這是我以前的「迷你出貨箱」，給你。^下次你拿到配得上「皮埃爾優選」名號的產品的時候，考慮一下把它們賣到我這來？^^——皮埃爾%item bigobject 248 %%[#]皮埃爾優選",
        "MSB_Lewis": "@：^感謝你幫我完成特別訂單。你所付出的努力極大地提升了鵜鶘鎮的形象。^給你一個「迷你出貨箱」表達我對你的感謝。^把它放在哪裡都行，輪到我巡視的時候一定會處理好的。^^——路易斯%item bigobject 248 %%[#]路易斯的感謝",
        "WizardReward": "你提供的標本讓我深入了解了我們稱之為「怪物」的墮落生物的陰謀。^^我配置了一種氣味刺激的藥酒，可以讓這些怪物陶醉，使用時要小心……^^——法師 M·拉斯莫迪斯%item craftingRecipe Monster_Musk %%[#]法師的發現",
        "WizardReward2": "多虧你送來的靈外質，我的奧術有了重要突破。^^隨信附上一張非常實用的機器的設計圖……^^——法師 M·拉斯莫迪斯%item craftingRecipe Mini-Obelisk %%[#]法師的突破",
        "DemetriusReward": "@：^^你好！^^感謝你幫我處理了魚的問題。^大自然通常自己會保持平衡，但有時人為因素會破壞生態平衡。^^隨信附上來自科學雜誌的一份設計圖，你可能會感興趣。^^——德米特里厄斯%item craftingRecipe Farm_Computer %%[#]德米特里厄斯的感謝",
        "willyHours": "好消息！^^多虧了你，這艘船又能出海了！^^你想出航的話隨時到裡屋來就行。^^我的店現在每天早上 8 點開門，所以你想早點出發也可以。^^——威利[#]威利的船",
        "linusTrashCleanup": "@：^^你好。^^謝謝你幫忙清理山谷。^水看起來清澈多了。謝謝你，而且我想大家都會感謝你的。^為了表達「感謝」，我想教你種植纖維的方法。希望能幫到你。^^——萊納斯%item craftingRecipe Fiber_Seeds %%[#]萊納斯的感謝",
        "gusGiantOmelet": "@：^^你好。^^感謝你給的蛋。^這蛋黃看起來品質很棒……我覺得這會是我做過的最好的煎蛋卷！^^請收下這份禮物。^^——格斯%item bigobject 216 %%[#]格斯的著名煎蛋卷",
        "pamNewChannel": "孩子，你好：^^感謝你的「果汁」。它的確有一種……「獨特」的風味^^順便問一下，你有沒有看過 736 頻道？是一個季節性捕撈節目，你可能感興趣。^^多多保重。^——潘姆[#]潘姆的提示",
        "emilyStones": "@：^^你好。^^再次感謝你送給我的寶石，它們品質很好。^我的能量調息用這些寶石正正好好！^我想用這份特別的禮物表示我的感謝。希望你能用它做出更多好東西！^^——艾米麗%item bigobject 247 %%[#]艾米麗的寶石",
        "carolineSO": "@：^^你好。^^路易斯告訴我你從島上運了很多食材過來！有機會接觸新的材料真是太好了……這樣我就能繼續在烹飪上大顯身手了！^我給你準備了一份禮物……是你可能用得上的設計圖。^^——卡洛琳%item craftingRecipe Solar_Panel %%[#]卡洛琳的熱帶食材",
        "WillyTropicalFish": "@：^^祝賀你的海島釣魚之旅取得成功。為你感到驕傲！^^給，收下這個特製的魚缸。它會成為你家的一大亮點。^^——威利%item furniture 2312 %%[#]威利的熱帶挑戰",
        "passedOutIsland": "@：^^在船上沒發現你，所以我就去找你了。^^結果發現你躺在泥裡，而且還有幾隻鸚鵡正從你口袋裡掏金幣！^^之後我一路把你拖回了船上。現在我的腿軟得跟蝦一樣……^——威利",
        "passedOutIsland_Leo": "@：^^你好。^^昨晚我發現你在暗處睡著了。^那個地方不太安全，所以鳥兒朋友們把你空運到了床上。^之後還請多注意安全。^^——雷歐^^P.S. 這封信是威利幫我寫的。",
        "guntherBones": "@：^^你好。^^謝謝你提供的骨頭。它們正等著我去研究！你想想，每一塊骨頭都曾屬於一個活著的遠古生命，多麼迷人。^^這是給你的感謝禮物，請收下這份獨特的工藝配方！^^——岡瑟%item craftingRecipe Bone_Mill %%[#]岡瑟的便條",
        "LeoCooking": "@：^這是我從家裡拿來的食物，我和我的親屬都很喜歡，希望你也能喜歡。^^——雷歐^^P.S. 是威利幫我寫的。%item cookingRecipe %%[#]雷歐的食譜"
    }
}