{
    "header": {
        "target": "w",
        "formatVersion": 5,
        "hidef": true,
        "compressed": 128
    },
    "readers": [
        {
            "type": "Microsoft.Xna.Framework.Content.DictionaryReader`2[[System.String, mscorlib, Version=4.0.0.0, Culture=neutral, PublicKeyToken=b77a5c561934e089],[System.String, mscorlib, Version=4.0.0.0, Culture=neutral, PublicKeyToken=b77a5c561934e089]]",
            "version": 0
        },
        {
            "type": "Microsoft.Xna.Framework.Content.StringReader",
            "version": 0
        }
    ],
    "content": {
        "ScienceHouse_Robin_Raining1": "這天氣真讓人受罪啊，是吧？",
        "ScienceHouse_Robin_Raining2": "糟糕，你全身濕透了！",
        "ScienceHouse_Robin_NotRaining1": "嘿，散步回來了嗎？",
        "ScienceHouse_Robin_NotRaining2": "嘿！",
        "ScienceHouse_Robin_Snowing": "這裡好暖和好舒適！",
        "ScienceHouse_Robin_NotSnowing": "你好啊！",
        "ScienceHouse_Robin_CloseFriends": "嗨，{0}！",
        "ScienceHouse_Robin_NotCloseFriends": "需要建造些什麼東西嗎？",
        "ScienceHouse_Robin_Greeting": "歡迎！",
        "ScienceHouse_Robin_RareGreeting": "劉……？噢！",
        "AnimalShop_Marnie_Greeting1": "你好！",
        "AnimalShop_Marnie_Greeting2": "你好！",
        "AnimalShop_Marnie_CloseFriends": "你好, {0}",
        "AnimalShop_Marnie_NotCloseFriends": "是想來購置補給品嗎？",
        "AnimalShop_Marnie_Raining": "把你的腳擦乾！",
        "AnimalShop_Marnie_NotRaining": "嗨！最近天氣還好嗎？",
        "AnimalShop_Marnie_Greeting3": "嗨！{1}農場最近如何了？",
        "AnimalShop_Marnie_RareGreeting": "劉……？噢！",
        "AdventureGuild_Marlon_Greeting_Male": "他回來了！",
        "AdventureGuild_Marlon_Greeting_Female": "她回來了！",
        "AdventureGuild_Marlon_Greeting1": "是來買劍的嗎？",
        "AdventureGuild_Marlon_Greeting2": "你好啊。",
        "AdventureGuild_Marlon_Greeting3": "吉爾，醒醒！有客人來了。",
        "AdventureGuild_Marlon_Greeting4": "晚安。",
        "Hospital_Maru_Greeting1": "您有預約嗎？",
        "Hospital_Maru_Greeting2": "我能幫您嗎？",
        "Hospital_Maru_Greeting3": "我們這裡出售藥物！",
        "Hospital_Maru_Greeting4": "是緊急情況嗎？",
        "Hospital_Maru_Greeting5": "來看醫生的嗎？",
        "Hospital_Maru_Spouse": "嗨，甜心<",
        "LeahHouse_Leah_Greeting1": "啊，你好！",
        "LeahHouse_Leah_Greeting2": "你好。",
        "LeahHouse_Leah_Greeting3": "你好, {0}",
        "ElliottHouse_Elliott_Greeting1": "謝謝光臨。",
        "ElliottHouse_Elliott_Greeting2": "你好。",
        "ElliottHouse_Elliott_Greeting3": "你好，{0}",
        "JojaMart_Morris_Greeting": "歡迎來到Joja超市！",
        "SandyHouse_Sandy_Greeting1": "真可憐，都被曬傷了！",
        "SandyHouse_Sandy_Greeting2": "哦，有客人來了！",
        "SandyHouse_Sandy_Greeting3": "你看起來口乾舌燥！",
        "SandyHouse_Sandy_Greeting4": "出售稀有種子！",
        "SandyHouse_Sandy_Greeting5": "親愛的，你不買點什麼嗎？",
        "ManorHouse_Lewis_Morning": "早安！",
        "ManorHouse_Lewis_Afternoon": "午安。",
        "ManorHouse_Lewis_Evening": "晚安。",
        "Saloon_Gus_Greeting": "請進請進！",
        "Saloon_Gus_Summer": "想要喝點什麼嗎？",
        "Saloon_Gus_NotSummer": "您需要點什麼？",
        "Saloon_Gus_Snowing1": "外面很冷，咖啡很暖和！",
        "Saloon_Gus_NotSnowing1": "想要吃點熱食嗎？",
        "Saloon_Gus_Raining": "需要一杯熱飲嗎？",
        "Saloon_Gus_NotRaining": "想要喝點什麼嗎？",
        "Saloon_Gus_Snowing2": "進來禦寒吧！",
        "Saloon_Gus_NotSnowing2": "歡迎！",
        "Saloon_Gus_RareGreeting": "你似乎需要喝點東西。",
        "ArchaeologyHouse_Gunther_Greeting1": "找到什麼了嗎？",
        "ArchaeologyHouse_Gunther_Greeting2": "挖出什麼了嗎？",
        "ArchaeologyHouse_Gunther_Greeting3": "需要我幫忙是嗎？",
        "ArchaeologyHouse_Gunther_Greeting4": "你好。",
        "ArchaeologyHouse_Gunther_Greeting5": "有東西帶給我是嗎？",
        "ArchaeologyHouse_Gunther_RareGreeting": "你身上有泥土的味道……不錯！",
        "SeedShop_Pierre_Winter": "歡迎來到熱氣騰騰的皮埃爾種子店！",
        "SeedShop_Pierre_NotWinter": "歡迎來到皮埃爾種子店！",
        "SeedShop_Pierre_Summer": "夏季種子有售！",
        "SeedShop_Pierre_NotSummer": "種子出售！",
        "SeedShop_Pierre_Greeting1": "你好！",
        "SeedShop_Pierre_Greeting2": "是農夫{0}！",
        "SeedShop_Pierre_Raining": "今天風和日麗，適合購物！",
        "SeedShop_Pierre_NotRaining": "歡迎！",
        "SeedShop_Pierre_RareGreeting": "你帶錢包了吧？"
    }
}
